setup.py
lin_alg_djl/__init__.py
lin_alg_djl/hyperplane.py
lin_alg_djl/lin_sys.py
lin_alg_djl/line.py
lin_alg_djl/plane.py
lin_alg_djl/vector.py
lin_alg_djl.egg-info/PKG-INFO
lin_alg_djl.egg-info/SOURCES.txt
lin_alg_djl.egg-info/dependency_links.txt
lin_alg_djl.egg-info/not-zip-safe
lin_alg_djl.egg-info/top_level.txt