Metadata-Version: 1.0
Name: lin-alg-djl
Version: 0.1
Summary: Linear Algebra Tools from Udacity
Home-page: UNKNOWN
Author: Derrick Lewis
Author-email: UNKNOWN
License: UNKNOWN
Platform: UNKNOWN
